chitboxes/__init__.py
chitboxes/chitboxes.py
chitboxes-0.0.1.dist-info/LICENSE.md
chitboxes-0.0.1.dist-info/METADATA
chitboxes-0.0.1.dist-info/WHEEL
chitboxes-0.0.1.dist-info/entry_points.txt
chitboxes-0.0.1.dist-info/top_level.txt
chitboxes-0.0.1.dist-info/RECORD
