Metadata-Version: 2.1
Name: chitboxes
Version: 0.0.1
Summary: Chitbox Generation for Board- and Cardgames
Home-page: http://domtabs.sandflea.org
Author: Peter Gorniak
Author-email: sumpfork@mailmight.net
License: UNKNOWN
Keywords: boardgame,cardgame,chitboxes
Platform: UNKNOWN
Requires-Dist: reportlab (>=3.4.0)
Requires-Dist: Pillow (>=4.1.0)
Requires-Dist: numpy
